friendlly/__init__.py
friendlly/_modidx.py
friendlly/capture_display.py
friendlly/capture_io.py
friendlly/capture_trace.py
friendlly/config.py
friendlly/display.py
friendlly/magic_cell.py
friendlly/magic_line.py
friendlly/notebook.py
friendlly/utils.py
friendlly-0.2.7.dist-info/LICENSE
friendlly-0.2.7.dist-info/METADATA
friendlly-0.2.7.dist-info/WHEEL
friendlly-0.2.7.dist-info/entry_points.txt
friendlly-0.2.7.dist-info/top_level.txt
friendlly-0.2.7.dist-info/RECORD
