Metadata-Version: 2.1
Name: friendlly
Version: 0.2.7
Summary: Your friendlly ai assistant
Home-page: https://github.com/xl0/friendlly
Author: Alexey
Author-email: alexey.zaytsev@gmail.com
License: Apache Software License 2.0
Keywords: nbdev jupyter notebook python
Classifier: Development Status :: 4 - Beta
Classifier: Intended Audience :: Developers
Classifier: Natural Language :: English
Classifier: Programming Language :: Python :: 3.7
Classifier: Programming Language :: Python :: 3.8
Classifier: Programming Language :: Python :: 3.9
Classifier: Programming Language :: Python :: 3.10
Classifier: License :: OSI Approved :: Apache Software License
Requires-Python: >=3.7
License-File: LICENSE
Requires-Dist: claudette >=0.0.5
Requires-Dist: cairosvg
Requires-Dist: psutil
Provides-Extra: dev
Requires-Dist: python-dotenv ; extra == 'dev'
Requires-Dist: pillow ; extra == 'dev'
